octoml_profile/README.md
octoml_profile/__init__.py
octoml_profile/_about.py
octoml_profile/client.py
octoml_profile/conversion_util.py
octoml_profile/dynamo.py
octoml_profile/errors.py
octoml_profile/fx2proto.py
octoml_profile/inference_session.py
octoml_profile/interceptors/__init__.py
octoml_profile/interceptors/auth.py
octoml_profile/interceptors/base.py
octoml_profile/interceptors/cookie.py
octoml_profile/log_util.py
octoml_profile/patches/__init__.py
octoml_profile/patches/build_map_unpack.py
octoml_profile/patches/diffusers_output_type.py
octoml_profile/patches/dyn_shape_call_neg.py
octoml_profile/patches/iadd_tuple_tuple.py
octoml_profile/patches/user_defined_call.py
octoml_profile/pricing.py
octoml_profile/protos/fxgraph_pb2.py
octoml_profile/protos/fxgraph_pb2_grpc.py
octoml_profile/protos/inference_base_pb2.py
octoml_profile/protos/inference_base_pb2_grpc.py
octoml_profile/protos/remote_inference_pb2.py
octoml_profile/protos/remote_inference_pb2_grpc.py
octoml_profile/report.py
octoml_profile/shape.py
octoml_profile/workaround.py
octoml_profile-0.2.2.dist-info/LICENSE
octoml_profile-0.2.2.dist-info/WHEEL
octoml_profile-0.2.2.dist-info/METADATA
octoml_profile-0.2.2.dist-info/RECORD
